gbmarrsmodules/__init__.py
gbmarrsmodules/common.py
gbmarrsmodules/csim_etl_modules.py
gbmarrsmodules/miriamRegex.py
gbmarrsmodules/namespaces.py
gbmarrsmodules/project_graph_modules.py
gbmarrsmodules/rdfWriterValidated.py
gbmarrsmodules/rdfstream.py
gbmarrsmodules/util.py
gbmarrsmodules-1.0.4.dist-info/LICENSE
gbmarrsmodules-1.0.4.dist-info/METADATA
gbmarrsmodules-1.0.4.dist-info/WHEEL
gbmarrsmodules-1.0.4.dist-info/top_level.txt
gbmarrsmodules-1.0.4.dist-info/RECORD
