Metadata-Version: 2.1
Name: gbmarrsmodules
Version: 1.0.4
Summary: Shared common modules from General Bioinformatics
Home-page: https://gitlab.generalbioinformatics.com/dev-all/gbmarrsmodules
Author: Mike Way, Joanna Parmley, Eleanor Cottam
Author-email: mike.way@generalbioinformatics.com, joanna@generalbioinformatics.com
License: MIT
Platform: UNKNOWN
Requires-Python: >=3.6
License-File: LICENSE
Requires-Dist: rdflib
Requires-Dist: pandas
Requires-Dist: requests
Requires-Dist: psycopg2-binary
Requires-Dist: jinja2
Requires-Dist: jprops
